{
  "char": {
    "allSkillLvlup": [
      {
        "3301": 4
      },
      {
        "30041": 5,
        "3301": 4
      },
      {
        "30052": 3,
        "3302": 6
      },
      {
        "30062": 3,
        "3302": 6
      },
      {
        "30033": 5,
        "3302": 6
      },
      {
        "30043": 2,
        "30093": 3,
        "3303": 6
      }
    ],
    "description": "再部署时间大幅度<@ba.kw>减少</>",
    "favorKeyFrames": [
      {
        "atk": 0,
        "attackSpeed": 0.0,
        "baseAttackTime": 0.0,
        "baseForceLevel": 0,
        "blockCnt": 0,
        "cost": 0,
        "def": 0,
        "hpRecoveryPerSec": 0.0,
        "level": 0,
        "magicResistance": 0.0,
        "massLevel": 0,
        "maxDeckStackCnt": 0,
        "maxDeployCount": 0,
        "maxHp": 0,
        "respawnTime": 0,
        "spRecoveryPerSec": 0.0,
        "tauntLevel": 0
      },
      {
        "atk": 50,
        "attackSpeed": 0.0,
        "baseAttackTime": 0.0,
        "baseForceLevel": 0,
        "blockCnt": 0,
        "cost": 0,
        "def": 30,
        "hpRecoveryPerSec": 0.0,
        "level": 50,
        "magicResistance": 0.0,
        "massLevel": 0,
        "maxDeckStackCnt": 0,
        "maxDeployCount": 0,
        "maxHp": 0,
        "respawnTime": 0,
        "spRecoveryPerSec": 0.0,
        "tauntLevel": 0
      }
    ],
    "isSpChar": false,
    "itemObtainApproach": "招募寻访",
    "name": "槐琥",
    "phases": [
      {
        "attributesKeyFrames": [
          {
            "atk": 207,
            "attackSpeed": 100.0,
            "baseAttackTime": 0.93,
            "baseForceLevel": 0,
            "blockCnt": 1,
            "cost": 7,
            "def": 137,
            "hpRecoveryPerSec": 0.0,
            "level": 1,
            "magicResistance": 0.0,
            "massLevel": 0,
            "maxDeckStackCnt": 0,
            "maxDeployCount": 1,
            "maxHp": 680,
            "respawnTime": 18,
            "spRecoveryPerSec": 1.0,
            "tauntLevel": 0
          },
          {
            "atk": 305,
            "attackSpeed": 100.0,
            "baseAttackTime": 0.93,
            "baseForceLevel": 0,
            "blockCnt": 1,
            "cost": 7,
            "def": 196,
            "hpRecoveryPerSec": 0.0,
            "level": 50,
            "magicResistance": 0.0,
            "massLevel": 0,
            "maxDeckStackCnt": 0,
            "maxDeployCount": 1,
            "maxHp": 907,
            "respawnTime": 18,
            "spRecoveryPerSec": 1.0,
            "tauntLevel": 0
          }
        ],
        "characterPrefabKey": "char_243_waaifu",
        "evolveCost": null,
        "maxLevel": 50,
        "rangeId": "1-1"
      },
      {
        "attributesKeyFrames": [
          {
            "atk": 305,
            "attackSpeed": 100.0,
            "baseAttackTime": 0.93,
            "baseForceLevel": 0,
            "blockCnt": 1,
            "cost": 9,
            "def": 196,
            "hpRecoveryPerSec": 0.0,
            "level": 1,
            "magicResistance": 0.0,
            "massLevel": 0,
            "maxDeckStackCnt": 0,
            "maxDeployCount": 1,
            "maxHp": 907,
            "respawnTime": 18,
            "spRecoveryPerSec": 1.0,
            "tauntLevel": 0
          },
          {
            "atk": 418,
            "attackSpeed": 100.0,
            "baseAttackTime": 0.93,
            "baseForceLevel": 0,
            "blockCnt": 1,
            "cost": 9,
            "def": 255,
            "hpRecoveryPerSec": 0.0,
            "level": 70,
            "magicResistance": 0.0,
            "massLevel": 0,
            "maxDeckStackCnt": 0,
            "maxDeployCount": 1,
            "maxHp": 1134,
            "respawnTime": 18,
            "spRecoveryPerSec": 1.0,
            "tauntLevel": 0
          }
        ],
        "characterPrefabKey": "char_243_waaifu",
        "evolveCost": {
          "30022": 3,
          "30042": 4,
          "3281": 4
        },
        "maxLevel": 70,
        "rangeId": "1-1"
      },
      {
        "attributesKeyFrames": [
          {
            "atk": 418,
            "attackSpeed": 100.0,
            "baseAttackTime": 0.93,
            "baseForceLevel": 0,
            "blockCnt": 1,
            "cost": 9,
            "def": 255,
            "hpRecoveryPerSec": 0.0,
            "level": 1,
            "magicResistance": 0.0,
            "massLevel": 0,
            "maxDeckStackCnt": 0,
            "maxDeployCount": 1,
            "maxHp": 1134,
            "respawnTime": 18,
            "spRecoveryPerSec": 1.0,
            "tauntLevel": 0
          },
          {
            "atk": 536,
            "attackSpeed": 100.0,
            "baseAttackTime": 0.93,
            "baseForceLevel": 0,
            "blockCnt": 1,
            "cost": 9,
            "def": 304,
            "hpRecoveryPerSec": 0.0,
            "level": 80,
            "magicResistance": 0.0,
            "massLevel": 0,
            "maxDeckStackCnt": 0,
            "maxDeployCount": 1,
            "maxHp": 1455,
            "respawnTime": 18,
            "spRecoveryPerSec": 1.0,
            "tauntLevel": 0
          }
        ],
        "characterPrefabKey": "char_243_waaifu",
        "evolveCost": {
          "30013": 16,
          "30104": 7,
          "3283": 3
        },
        "maxLevel": 80,
        "rangeId": "1-1"
      }
    ],
    "potentialRanks": [
      {
        "attributeType": "COST",
        "description": "部署费用-1",
        "formulaItem": "ADDITION",
        "type": "BUFF",
        "value": -1.0
      },
      {
        "attributeType": "DEF",
        "description": "防御力+19",
        "formulaItem": "ADDITION",
        "type": "BUFF",
        "value": 19.0
      },
      {
        "attributeType": "RESPAWN_TIME",
        "description": "再部署时间-2秒",
        "formulaItem": "ADDITION",
        "type": "BUFF",
        "value": -2.0
      },
      {
        "buff": null,
        "description": "天赋效果增强",
        "type": "CUSTOM"
      },
      {
        "attributeType": "COST",
        "description": "部署费用-1",
        "formulaItem": "ADDITION",
        "type": "BUFF",
        "value": -1.0
      }
    ],
    "profession": "SPECIAL",
    "rarity": 5,
    "skills": [
      {
        "levelUpCostCond": [
          {
            "30033": 3,
            "30054": 3,
            "3303": 5
          },
          {
            "30054": 5,
            "30074": 3,
            "3303": 6
          },
          {
            "30064": 3,
            "30135": 4,
            "3303": 10
          }
        ],
        "overridePrefabKey": null,
        "overrideTokenKey": null,
        "skillId": "skchr_waaifu_1"
      },
      {
        "levelUpCostCond": [
          {
            "30043": 3,
            "30064": 2,
            "3303": 5
          },
          {
            "30064": 4,
            "30084": 3,
            "3303": 6
          },
          {
            "30034": 4,
            "30115": 4,
            "3303": 10
          }
        ],
        "overridePrefabKey": null,
        "overrideTokenKey": null,
        "skillId": "skchr_waaifu_2"
      }
    ],
    "subProfessionId": "executor",
    "talents": [
      [
        {
          "blackboard": {
            "atk_scale": 1.25,
            "force": -1.0,
            "prob": 0.2
          },
          "description": "攻击时有20%的几率攻击力提升至125%，并将目标稍微击退",
          "name": "红眉咏春",
          "prefabKey": "1",
          "rangeId": null,
          "requiredPotentialRank": 0,
          "tokenKey": null,
          "unlockCondition": {
            "level": 1,
            "phase": 1
          }
        },
        {
          "blackboard": {
            "atk_scale": 1.35,
            "force": -1.0,
            "prob": 0.2
          },
          "description": "攻击时有20%的几率攻击力提升至135%<@ba.talpu>（+10%）</>，并将目标稍微击退",
          "name": "红眉咏春",
          "prefabKey": "1",
          "rangeId": null,
          "requiredPotentialRank": 4,
          "tokenKey": null,
          "unlockCondition": {
            "level": 1,
            "phase": 1
          }
        },
        {
          "blackboard": {
            "atk_scale": 1.5,
            "force": -1.0,
            "prob": 0.2
          },
          "description": "攻击时有20%的几率攻击力提升至150%，并将目标稍微地击退",
          "name": "红眉咏春",
          "prefabKey": "1",
          "rangeId": null,
          "requiredPotentialRank": 0,
          "tokenKey": null,
          "unlockCondition": {
            "level": 1,
            "phase": 2
          }
        },
        {
          "blackboard": {
            "atk_scale": 1.6,
            "force": -1.0,
            "prob": 0.2
          },
          "description": "攻击时有20%的几率攻击力提升至160%<@ba.talpu>（+10%）</>，并将目标稍微地击退",
          "name": "红眉咏春",
          "prefabKey": "1",
          "rangeId": null,
          "requiredPotentialRank": 4,
          "tokenKey": null,
          "unlockCondition": {
            "level": 1,
            "phase": 2
          }
        }
      ]
    ],
    "trait": null
  },
  "custom": {
    "anim": {
      "Attack": {
        "OnAttack": 14,
        "duration": 30
      },
      "Idle": 30,
      "Start": {
        "OnStart": 5,
        "duration": 30
      },
      "Start_2": {
        "OnAttack": 14,
        "OnStart": 5,
        "duration": 30
      }
    },
    "options": {
      "cond_info": null,
      "tags": [
        "crit",
        "equip"
      ]
    },
    "spec": {
      "tachr_243_waaifu_1": {
        "crit": true
      }
    }
  },
  "equip": {
    "uniequip_001_waaifu": {
      "battle": null,
      "charId": "char_243_waaifu",
      "itemCost": null,
      "typeIcon": "original",
      "uniEquipId": "uniequip_001_waaifu",
      "uniEquipName": "槐琥证章"
    },
    "uniequip_002_waaifu": {
      "battle": [
        {
          "attributeBlackboard": {
            "atk": 45.0,
            "max_hp": 70.0
          },
          "equipLevel": 1,
          "parts": [
            {
              "addOrOverrideTalentDataBundle": null,
              "isToken": false,
              "overrideTraitDataBundle": [
                {
                  "additionalDescription": "撤退时返还<@ba.kw>大量</>该次部署费用",
                  "blackboard": {
                    "withdraw_cost_recover_ratio": 0.8
                  },
                  "overrideDescripton": null,
                  "prefabKey": null,
                  "rangeId": null,
                  "requiredPotentialRank": 0,
                  "unlockCondition": {
                    "level": 50,
                    "phase": 2
                  }
                }
              ],
              "resKey": "waaifu_equip_1_2_p1",
              "target": "TRAIT",
              "validInGameTag": null
            }
          ],
          "tokenAttributeBlackboard": null
        },
        {
          "attributeBlackboard": {
            "atk": 55.0,
            "max_hp": 85.0
          },
          "equipLevel": 2,
          "parts": [
            {
              "addOrOverrideTalentDataBundle": null,
              "isToken": false,
              "overrideTraitDataBundle": [
                {
                  "additionalDescription": "撤退时返还<@ba.kw>大量</>该次部署费用",
                  "blackboard": {
                    "withdraw_cost_recover_ratio": 0.8
                  },
                  "overrideDescripton": null,
                  "prefabKey": null,
                  "rangeId": null,
                  "requiredPotentialRank": 0,
                  "unlockCondition": {
                    "level": 50,
                    "phase": 2
                  }
                }
              ],
              "resKey": "waaifu_equip_1_2_p1",
              "target": "TRAIT",
              "validInGameTag": null
            },
            {
              "addOrOverrideTalentDataBundle": [
                {
                  "blackboard": {
                    "atk_scale": 1.07
                  },
                  "description": null,
                  "displayRangeId": false,
                  "isHideTalent": false,
                  "name": "除害杂役",
                  "prefabKey": "10",
                  "rangeId": null,
                  "requiredPotentialRank": 0,
                  "talentIndex": -1,
                  "tokenKey": null,
                  "unlockCondition": {
                    "level": 50,
                    "phase": 2
                  },
                  "upgradeDescription": "对【感染生物】造成的物理伤害提升7%"
                }
              ],
              "isToken": false,
              "overrideTraitDataBundle": null,
              "resKey": "waaifu_equip_1_2_p2",
              "target": "TALENT",
              "validInGameTag": null
            }
          ],
          "tokenAttributeBlackboard": null
        },
        {
          "attributeBlackboard": {
            "atk": 65.0,
            "max_hp": 95.0
          },
          "equipLevel": 3,
          "parts": [
            {
              "addOrOverrideTalentDataBundle": null,
              "isToken": false,
              "overrideTraitDataBundle": [
                {
                  "additionalDescription": "撤退时返还<@ba.kw>大量</>该次部署费用",
                  "blackboard": {
                    "withdraw_cost_recover_ratio": 0.8
                  },
                  "overrideDescripton": null,
                  "prefabKey": null,
                  "rangeId": null,
                  "requiredPotentialRank": 0,
                  "unlockCondition": {
                    "level": 50,
                    "phase": 2
                  }
                }
              ],
              "resKey": "waaifu_equip_1_3_p1",
              "target": "TRAIT",
              "validInGameTag": null
            },
            {
              "addOrOverrideTalentDataBundle": [
                {
                  "blackboard": {
                    "atk_scale": 1.14
                  },
                  "description": null,
                  "displayRangeId": false,
                  "isHideTalent": false,
                  "name": "除害杂役",
                  "prefabKey": "10",
                  "rangeId": null,
                  "requiredPotentialRank": 0,
                  "talentIndex": -1,
                  "tokenKey": null,
                  "unlockCondition": {
                    "level": 50,
                    "phase": 2
                  },
                  "upgradeDescription": "对【感染生物】造成的物理伤害提升14%"
                }
              ],
              "isToken": false,
              "overrideTraitDataBundle": null,
              "resKey": "waaifu_equip_1_3_p2",
              "target": "TALENT",
              "validInGameTag": null
            }
          ],
          "tokenAttributeBlackboard": null
        }
      ],
      "charId": "char_243_waaifu",
      "itemCost": {
        "1": {
          "31014": 3,
          "4001": 40000,
          "mod_unlock_token": 2
        },
        "2": {
          "30064": 4,
          "4001": 50000,
          "mod_unlock_token": 2,
          "mod_update_token_1": 20
        },
        "3": {
          "30014": 5,
          "4001": 60000,
          "mod_unlock_token": 2,
          "mod_update_token_2": 8
        }
      },
      "typeIcon": "exe-x",
      "uniEquipId": "uniequip_002_waaifu",
      "uniEquipName": "红眉咏春拳谱"
    }
  },
  "skill": {
    "skchr_waaifu_1": [
      {
        "blackboard": {
          "attack@waaifu_s_1[debuff].atk": -0.2,
          "attack@waaifu_s_1[debuff].duration": 2.0,
          "waaifu_s_1[self].atk": 0.25
        },
        "description": "部署后攻击力<@ba.vup>+{waaifu_s_1[self].atk:0%}</>，并使被攻击目标在<@ba.vup>{attack@waaifu_s_1[debuff].duration}</>秒内攻击力<@ba.vup>-{-attack@waaifu_s_1[debuff].atk:0%}</>",
        "duration": 10.0,
        "durationType": "NONE",
        "name": "寸劲",
        "prefabId": "skchr_waaifu_1",
        "rangeId": null,
        "skillType": "PASSIVE",
        "spData": {
          "increment": 0.0,
          "initSp": 0,
          "levelUpCost": null,
          "maxChargeTime": 0,
          "spCost": 0,
          "spType": 8
        }
      },
      {
        "blackboard": {
          "attack@waaifu_s_1[debuff].atk": -0.2,
          "attack@waaifu_s_1[debuff].duration": 2.0,
          "waaifu_s_1[self].atk": 0.3
        },
        "description": "部署后攻击力<@ba.vup>+{waaifu_s_1[self].atk:0%}</>，并使被攻击目标在<@ba.vup>{attack@waaifu_s_1[debuff].duration}</>秒内攻击力<@ba.vup>-{-attack@waaifu_s_1[debuff].atk:0%}</>",
        "duration": 10.0,
        "durationType": "NONE",
        "name": "寸劲",
        "prefabId": "skchr_waaifu_1",
        "rangeId": null,
        "skillType": "PASSIVE",
        "spData": {
          "increment": 0.0,
          "initSp": 0,
          "levelUpCost": null,
          "maxChargeTime": 0,
          "spCost": 0,
          "spType": 8
        }
      },
      {
        "blackboard": {
          "attack@waaifu_s_1[debuff].atk": -0.2,
          "attack@waaifu_s_1[debuff].duration": 2.0,
          "waaifu_s_1[self].atk": 0.35
        },
        "description": "部署后攻击力<@ba.vup>+{waaifu_s_1[self].atk:0%}</>，并使被攻击目标在<@ba.vup>{attack@waaifu_s_1[debuff].duration}</>秒内攻击力<@ba.vup>-{-attack@waaifu_s_1[debuff].atk:0%}</>",
        "duration": 10.0,
        "durationType": "NONE",
        "name": "寸劲",
        "prefabId": "skchr_waaifu_1",
        "rangeId": null,
        "skillType": "PASSIVE",
        "spData": {
          "increment": 0.0,
          "initSp": 0,
          "levelUpCost": null,
          "maxChargeTime": 0,
          "spCost": 0,
          "spType": 8
        }
      },
      {
        "blackboard": {
          "attack@waaifu_s_1[debuff].atk": -0.25,
          "attack@waaifu_s_1[debuff].duration": 2.0,
          "waaifu_s_1[self].atk": 0.4
        },
        "description": "部署后攻击力<@ba.vup>+{waaifu_s_1[self].atk:0%}</>，并使被攻击目标在<@ba.vup>{attack@waaifu_s_1[debuff].duration}</>秒内攻击力<@ba.vup>-{-attack@waaifu_s_1[debuff].atk:0%}</>",
        "duration": 10.0,
        "durationType": "NONE",
        "name": "寸劲",
        "prefabId": "skchr_waaifu_1",
        "rangeId": null,
        "skillType": "PASSIVE",
        "spData": {
          "increment": 0.0,
          "initSp": 0,
          "levelUpCost": null,
          "maxChargeTime": 0,
          "spCost": 0,
          "spType": 8
        }
      },
      {
        "blackboard": {
          "attack@waaifu_s_1[debuff].atk": -0.25,
          "attack@waaifu_s_1[debuff].duration": 2.0,
          "waaifu_s_1[self].atk": 0.45
        },
        "description": "部署后攻击力<@ba.vup>+{waaifu_s_1[self].atk:0%}</>，并使被攻击目标在<@ba.vup>{attack@waaifu_s_1[debuff].duration}</>秒内攻击力<@ba.vup>-{-attack@waaifu_s_1[debuff].atk:0%}</>",
        "duration": 10.0,
        "durationType": "NONE",
        "name": "寸劲",
        "prefabId": "skchr_waaifu_1",
        "rangeId": null,
        "skillType": "PASSIVE",
        "spData": {
          "increment": 0.0,
          "initSp": 0,
          "levelUpCost": null,
          "maxChargeTime": 0,
          "spCost": 0,
          "spType": 8
        }
      },
      {
        "blackboard": {
          "attack@waaifu_s_1[debuff].atk": -0.25,
          "attack@waaifu_s_1[debuff].duration": 2.0,
          "waaifu_s_1[self].atk": 0.5
        },
        "description": "部署后攻击力<@ba.vup>+{waaifu_s_1[self].atk:0%}</>，并使被攻击目标在<@ba.vup>{attack@waaifu_s_1[debuff].duration}</>秒内攻击力<@ba.vup>-{-attack@waaifu_s_1[debuff].atk:0%}</>",
        "duration": 10.0,
        "durationType": "NONE",
        "name": "寸劲",
        "prefabId": "skchr_waaifu_1",
        "rangeId": null,
        "skillType": "PASSIVE",
        "spData": {
          "increment": 0.0,
          "initSp": 0,
          "levelUpCost": null,
          "maxChargeTime": 0,
          "spCost": 0,
          "spType": 8
        }
      },
      {
        "blackboard": {
          "attack@waaifu_s_1[debuff].atk": -0.3,
          "attack@waaifu_s_1[debuff].duration": 3.0,
          "waaifu_s_1[self].atk": 0.55
        },
        "description": "部署后攻击力<@ba.vup>+{waaifu_s_1[self].atk:0%}</>，并使被攻击目标在<@ba.vup>{attack@waaifu_s_1[debuff].duration}</>秒内攻击力<@ba.vup>-{-attack@waaifu_s_1[debuff].atk:0%}</>",
        "duration": 10.0,
        "durationType": "NONE",
        "name": "寸劲",
        "prefabId": "skchr_waaifu_1",
        "rangeId": null,
        "skillType": "PASSIVE",
        "spData": {
          "increment": 0.0,
          "initSp": 0,
          "levelUpCost": null,
          "maxChargeTime": 0,
          "spCost": 0,
          "spType": 8
        }
      },
      {
        "blackboard": {
          "attack@waaifu_s_1[debuff].atk": -0.33,
          "attack@waaifu_s_1[debuff].duration": 3.0,
          "waaifu_s_1[self].atk": 0.6
        },
        "description": "部署后攻击力<@ba.vup>+{waaifu_s_1[self].atk:0%}</>，并使被攻击目标在<@ba.vup>{attack@waaifu_s_1[debuff].duration}</>秒内攻击力<@ba.vup>-{-attack@waaifu_s_1[debuff].atk:0%}</>",
        "duration": 10.0,
        "durationType": "NONE",
        "name": "寸劲",
        "prefabId": "skchr_waaifu_1",
        "rangeId": null,
        "skillType": "PASSIVE",
        "spData": {
          "increment": 0.0,
          "initSp": 0,
          "levelUpCost": null,
          "maxChargeTime": 0,
          "spCost": 0,
          "spType": 8
        }
      },
      {
        "blackboard": {
          "attack@waaifu_s_1[debuff].atk": -0.36,
          "attack@waaifu_s_1[debuff].duration": 3.0,
          "waaifu_s_1[self].atk": 0.65
        },
        "description": "部署后攻击力<@ba.vup>+{waaifu_s_1[self].atk:0%}</>，并使被攻击目标在<@ba.vup>{attack@waaifu_s_1[debuff].duration}</>秒内攻击力<@ba.vup>-{-attack@waaifu_s_1[debuff].atk:0%}</>",
        "duration": 10.0,
        "durationType": "NONE",
        "name": "寸劲",
        "prefabId": "skchr_waaifu_1",
        "rangeId": null,
        "skillType": "PASSIVE",
        "spData": {
          "increment": 0.0,
          "initSp": 0,
          "levelUpCost": null,
          "maxChargeTime": 0,
          "spCost": 0,
          "spType": 8
        }
      },
      {
        "blackboard": {
          "attack@waaifu_s_1[debuff].atk": -0.4,
          "attack@waaifu_s_1[debuff].duration": 3.0,
          "waaifu_s_1[self].atk": 0.7
        },
        "description": "部署后攻击力<@ba.vup>+{waaifu_s_1[self].atk:0%}</>，并使被攻击目标在<@ba.vup>{attack@waaifu_s_1[debuff].duration}</>秒内攻击力<@ba.vup>-{-attack@waaifu_s_1[debuff].atk:0%}</>",
        "duration": 10.0,
        "durationType": "NONE",
        "name": "寸劲",
        "prefabId": "skchr_waaifu_1",
        "rangeId": null,
        "skillType": "PASSIVE",
        "spData": {
          "increment": 0.0,
          "initSp": 0,
          "levelUpCost": null,
          "maxChargeTime": 0,
          "spCost": 0,
          "spType": 8
        }
      }
    ],
    "skchr_waaifu_2": [
      {
        "blackboard": {
          "atk_scale": 1.8,
          "silence": 5.0
        },
        "description": "部署后立即对周围所有敌人造成相当于攻击力<@ba.vup>{atk_scale:0%}</>的物理伤害，并使命中目标失去特殊能力<@ba.vup>{silence}</>秒",
        "duration": 0.0,
        "durationType": "NONE",
        "name": "七武掠阵踢",
        "prefabId": "skchr_waaifu_2",
        "rangeId": "x-4",
        "skillType": "PASSIVE",
        "spData": {
          "increment": 0.0,
          "initSp": 0,
          "levelUpCost": null,
          "maxChargeTime": 0,
          "spCost": 0,
          "spType": 8
        }
      },
      {
        "blackboard": {
          "atk_scale": 1.9,
          "silence": 5.0
        },
        "description": "部署后立即对周围所有敌人造成相当于攻击力<@ba.vup>{atk_scale:0%}</>的物理伤害，并使命中目标失去特殊能力<@ba.vup>{silence}</>秒",
        "duration": 0.0,
        "durationType": "NONE",
        "name": "七武掠阵踢",
        "prefabId": "skchr_waaifu_2",
        "rangeId": "x-4",
        "skillType": "PASSIVE",
        "spData": {
          "increment": 0.0,
          "initSp": 0,
          "levelUpCost": null,
          "maxChargeTime": 0,
          "spCost": 0,
          "spType": 8
        }
      },
      {
        "blackboard": {
          "atk_scale": 2.0,
          "silence": 5.0
        },
        "description": "部署后立即对周围所有敌人造成相当于攻击力<@ba.vup>{atk_scale:0%}</>的物理伤害，并使命中目标失去特殊能力<@ba.vup>{silence}</>秒",
        "duration": 0.0,
        "durationType": "NONE",
        "name": "七武掠阵踢",
        "prefabId": "skchr_waaifu_2",
        "rangeId": "x-4",
        "skillType": "PASSIVE",
        "spData": {
          "increment": 0.0,
          "initSp": 0,
          "levelUpCost": null,
          "maxChargeTime": 0,
          "spCost": 0,
          "spType": 8
        }
      },
      {
        "blackboard": {
          "atk_scale": 2.1,
          "silence": 6.0
        },
        "description": "部署后立即对周围所有敌人造成相当于攻击力<@ba.vup>{atk_scale:0%}</>的物理伤害，并使命中目标失去特殊能力<@ba.vup>{silence}</>秒",
        "duration": 0.0,
        "durationType": "NONE",
        "name": "七武掠阵踢",
        "prefabId": "skchr_waaifu_2",
        "rangeId": "x-4",
        "skillType": "PASSIVE",
        "spData": {
          "increment": 0.0,
          "initSp": 0,
          "levelUpCost": null,
          "maxChargeTime": 0,
          "spCost": 0,
          "spType": 8
        }
      },
      {
        "blackboard": {
          "atk_scale": 2.2,
          "silence": 6.0
        },
        "description": "部署后立即对周围所有敌人造成相当于攻击力<@ba.vup>{atk_scale:0%}</>的物理伤害，并使命中目标失去特殊能力<@ba.vup>{silence}</>秒",
        "duration": 0.0,
        "durationType": "NONE",
        "name": "七武掠阵踢",
        "prefabId": "skchr_waaifu_2",
        "rangeId": "x-4",
        "skillType": "PASSIVE",
        "spData": {
          "increment": 0.0,
          "initSp": 0,
          "levelUpCost": null,
          "maxChargeTime": 0,
          "spCost": 0,
          "spType": 8
        }
      },
      {
        "blackboard": {
          "atk_scale": 2.3,
          "silence": 6.0
        },
        "description": "部署后立即对周围所有敌人造成相当于攻击力<@ba.vup>{atk_scale:0%}</>的物理伤害，并使命中目标失去特殊能力<@ba.vup>{silence}</>秒",
        "duration": 0.0,
        "durationType": "NONE",
        "name": "七武掠阵踢",
        "prefabId": "skchr_waaifu_2",
        "rangeId": "x-4",
        "skillType": "PASSIVE",
        "spData": {
          "increment": 0.0,
          "initSp": 0,
          "levelUpCost": null,
          "maxChargeTime": 0,
          "spCost": 0,
          "spType": 8
        }
      },
      {
        "blackboard": {
          "atk_scale": 2.4,
          "silence": 7.0
        },
        "description": "部署后立即对周围所有敌人造成相当于攻击力<@ba.vup>{atk_scale:0%}</>的物理伤害，并使命中目标失去特殊能力<@ba.vup>{silence}</>秒",
        "duration": 0.0,
        "durationType": "NONE",
        "name": "七武掠阵踢",
        "prefabId": "skchr_waaifu_2",
        "rangeId": "x-4",
        "skillType": "PASSIVE",
        "spData": {
          "increment": 0.0,
          "initSp": 0,
          "levelUpCost": null,
          "maxChargeTime": 0,
          "spCost": 0,
          "spType": 8
        }
      },
      {
        "blackboard": {
          "atk_scale": 2.55,
          "silence": 7.0
        },
        "description": "部署后立即对周围所有敌人造成相当于攻击力<@ba.vup>{atk_scale:0%}</>的物理伤害，并使命中目标失去特殊能力<@ba.vup>{silence}</>秒",
        "duration": 0.0,
        "durationType": "NONE",
        "name": "七武掠阵踢",
        "prefabId": "skchr_waaifu_2",
        "rangeId": "x-4",
        "skillType": "PASSIVE",
        "spData": {
          "increment": 0.0,
          "initSp": 0,
          "levelUpCost": null,
          "maxChargeTime": 0,
          "spCost": 0,
          "spType": 8
        }
      },
      {
        "blackboard": {
          "atk_scale": 2.7,
          "silence": 7.0
        },
        "description": "部署后立即对周围所有敌人造成相当于攻击力<@ba.vup>{atk_scale:0%}</>的物理伤害，并使命中目标失去特殊能力<@ba.vup>{silence}</>秒",
        "duration": 0.0,
        "durationType": "NONE",
        "name": "七武掠阵踢",
        "prefabId": "skchr_waaifu_2",
        "rangeId": "x-4",
        "skillType": "PASSIVE",
        "spData": {
          "increment": 0.0,
          "initSp": 0,
          "levelUpCost": null,
          "maxChargeTime": 0,
          "spCost": 0,
          "spType": 8
        }
      },
      {
        "blackboard": {
          "atk_scale": 2.9,
          "silence": 8.0
        },
        "description": "部署后立即对周围所有敌人造成相当于攻击力<@ba.vup>{atk_scale:0%}</>的物理伤害，并使命中目标失去特殊能力<@ba.vup>{silence}</>秒",
        "duration": 0.0,
        "durationType": "NONE",
        "name": "七武掠阵踢",
        "prefabId": "skchr_waaifu_2",
        "rangeId": "x-4",
        "skillType": "PASSIVE",
        "spData": {
          "increment": 0.0,
          "initSp": 0,
          "levelUpCost": null,
          "maxChargeTime": 0,
          "spCost": 0,
          "spType": 8
        }
      }
    ]
  }
}